lineage/__init__.py
lineage/_version.py
lineage/generator.py
lineage/individual.py
lineage/resources.py
lineage/visualization.py
lineage-4.5.0.dist-info/licenses/LICENSE.txt
lineage-4.5.0.dist-info/licenses/LICENSES-3RD-PARTY.txt
lineage-4.5.0.dist-info/METADATA
lineage-4.5.0.dist-info/WHEEL
lineage-4.5.0.dist-info/top_level.txt
lineage-4.5.0.dist-info/RECORD
