Metadata-Version: 2.4
Name: lineage
Version: 4.5.0
Summary: tools for analyzing and exploring genetic relationships
Home-page: https://github.com/apriha/lineage
Author: Andrew Riha
Author-email: apriha@gmail.com
License: MIT
Project-URL: Documentation, https://lineage.readthedocs.io
Project-URL: Changelog, https://github.com/apriha/lineage/releases
Project-URL: Issue Tracker, https://github.com/apriha/lineage/issues
Keywords: dna genes genetics genealogy snps chromosomes genotype bioinformatics ancestry
Platform: any
Classifier: Development Status :: 5 - Production/Stable
Classifier: Intended Audience :: Developers
Classifier: Intended Audience :: End Users/Desktop
Classifier: Intended Audience :: Healthcare Industry
Classifier: Intended Audience :: Science/Research
Classifier: License :: OSI Approved :: MIT License
Classifier: Natural Language :: English
Classifier: Operating System :: OS Independent
Classifier: Programming Language :: Python :: 3.9
Classifier: Programming Language :: Python :: 3.10
Classifier: Programming Language :: Python :: 3.11
Classifier: Programming Language :: Python :: 3.12
Classifier: Programming Language :: Python :: 3.13
Classifier: Programming Language :: Python :: 3.14
Classifier: Topic :: Scientific/Engineering
Classifier: Topic :: Scientific/Engineering :: Bio-Informatics
Classifier: Topic :: Scientific/Engineering :: Information Analysis
Classifier: Topic :: Scientific/Engineering :: Visualization
Classifier: Topic :: Utilities
Requires-Python: >=3.9
License-File: LICENSE.txt
License-File: LICENSES-3RD-PARTY.txt
Requires-Dist: numpy
Requires-Dist: pandas
Requires-Dist: matplotlib
Requires-Dist: atomicwrites
Requires-Dist: snps
Dynamic: author
Dynamic: author-email
Dynamic: classifier
Dynamic: description
Dynamic: description-content-type
Dynamic: home-page
Dynamic: keywords
Dynamic: license
Dynamic: license-file
Dynamic: platform
Dynamic: project-url
Dynamic: requires-dist
Dynamic: requires-python
Dynamic: summary
